odoo/addons/product_analytic_purchase/README.rst
odoo/addons/product_analytic_purchase/__init__.py
odoo/addons/product_analytic_purchase/__manifest__.py
odoo/addons/product_analytic_purchase/i18n/ca.po
odoo/addons/product_analytic_purchase/i18n/cs_CZ.po
odoo/addons/product_analytic_purchase/i18n/de.po
odoo/addons/product_analytic_purchase/i18n/es.po
odoo/addons/product_analytic_purchase/i18n/eu_ES.po
odoo/addons/product_analytic_purchase/i18n/fr.po
odoo/addons/product_analytic_purchase/i18n/hr.po
odoo/addons/product_analytic_purchase/i18n/it.po
odoo/addons/product_analytic_purchase/i18n/product_analytic_purchase.pot
odoo/addons/product_analytic_purchase/models/__init__.py
odoo/addons/product_analytic_purchase/models/purchase_order_line.py
odoo/addons/product_analytic_purchase/readme/CONTRIBUTORS.rst
odoo/addons/product_analytic_purchase/readme/DESCRIPTION.rst
odoo/addons/product_analytic_purchase/readme/USAGE.rst
odoo/addons/product_analytic_purchase/static/description/icon.png
odoo/addons/product_analytic_purchase/static/description/index.html
odoo/addons/product_analytic_purchase/tests/__init__.py
odoo/addons/product_analytic_purchase/tests/test_purchase.py
odoo_addon_product_analytic_purchase-16.0.1.0.0.8.dist-info/METADATA
odoo_addon_product_analytic_purchase-16.0.1.0.0.8.dist-info/WHEEL
odoo_addon_product_analytic_purchase-16.0.1.0.0.8.dist-info/top_level.txt
odoo_addon_product_analytic_purchase-16.0.1.0.0.8.dist-info/RECORD
